extractflow_parser/__init__.py
extractflow_parser/exceptions.py
extractflow_parser/llm.py
extractflow_parser/parser.py
extractflow_parser/img_analysis.prompt
extractflow_parser/md_prompt.j2
extractflow_parser-1.0.1.dist-info/METADATA
extractflow_parser-1.0.1.dist-info/WHEEL
extractflow_parser-1.0.1.dist-info/licenses/LICENSE
extractflow_parser-1.0.1.dist-info/RECORD
