Metadata-Version: 2.4
Name: extractflow_parser
Version: 1.0.1
Summary: Parse PDF documents into markdown formatted content using Vision LLMs
Project-URL: Homepage, https://github.com/simplifyX-ai/extractflow-parser
Project-URL: Repository, https://github.com/simplifyX-ai/extractflow-parser.git
Author-email: Chi Tran <chitran.whitecat@gmail.com>
License-Expression: MIT
License-File: LICENSE
Classifier: Development Status :: 3 - Alpha
Classifier: Intended Audience :: Developers
Classifier: License :: OSI Approved :: MIT License
Classifier: Programming Language :: Python :: 3
Classifier: Programming Language :: Python :: 3.9
Classifier: Programming Language :: Python :: 3.10
Classifier: Programming Language :: Python :: 3.11
Classifier: Programming Language :: Python :: 3.12
Classifier: Programming Language :: Python :: 3.13
Requires-Python: >=3.9
Requires-Dist: instructor>=1.7.2
Requires-Dist: jinja2>=3.0.0
Requires-Dist: ollama>=0.4.4
Requires-Dist: pydantic>=2.0.0
Requires-Dist: pymupdf>=1.22.0
Requires-Dist: tenacity>=9.0.0
Requires-Dist: tqdm>=4.65.0
Provides-Extra: all
Requires-Dist: google-generativeai==0.8.3; extra == 'all'
Requires-Dist: openai==1.58.0; extra == 'all'
Provides-Extra: dev
Requires-Dist: black>=24.4.1; extra == 'dev'
Requires-Dist: pytest>=8.3.4; extra == 'dev'
Requires-Dist: ruff>=0.8.3; extra == 'dev'
Provides-Extra: gemini
Requires-Dist: google-generativeai==0.8.3; extra == 'gemini'
Provides-Extra: openai
Requires-Dist: openai==1.58.0; extra == 'openai'
